LICENSE
MANIFEST.in
README.md
ez_setup.py
setup.py
res/snakejazz.png
res/snakejazz_medium.png
res/snakejazz_nano.png
res/snakejazz_small.png
snakejazz/__init__.py
snakejazz/snakejazz.py
snakejazz.egg-info/PKG-INFO
snakejazz.egg-info/SOURCES.txt
snakejazz.egg-info/dependency_links.txt
snakejazz.egg-info/requires.txt
snakejazz.egg-info/top_level.txt
snakejazz/sounds/__init__.py
snakejazz/sounds/rhodesmas/README.md
snakejazz/sounds/rhodesmas/__init__.py
snakejazz/sounds/rhodesmas/action-01.wav
snakejazz/sounds/rhodesmas/action-02.wav
snakejazz/sounds/rhodesmas/action-03.wav
snakejazz/sounds/rhodesmas/alert-01.wav
snakejazz/sounds/rhodesmas/alert-02.wav
snakejazz/sounds/rhodesmas/alert-03.wav
snakejazz/sounds/rhodesmas/alert-04.wav
snakejazz/sounds/rhodesmas/coins-purchase-01.wav
snakejazz/sounds/rhodesmas/coins-purchase-02.wav
snakejazz/sounds/rhodesmas/coins-purchase-3.wav
snakejazz/sounds/rhodesmas/coins-purchase-4.wav
snakejazz/sounds/rhodesmas/connected-01.wav
snakejazz/sounds/rhodesmas/connected-02.wav
snakejazz/sounds/rhodesmas/disconnected-01.wav
snakejazz/sounds/rhodesmas/disconnected-02.wav
snakejazz/sounds/rhodesmas/failure-01.wav
snakejazz/sounds/rhodesmas/incorrect-01.wav
snakejazz/sounds/rhodesmas/level-up-01.wav
snakejazz/sounds/rhodesmas/level-up-02.wav
snakejazz/sounds/rhodesmas/level-up-03.wav
snakejazz/sounds/rhodesmas/notification-01.wav
snakejazz/sounds/rhodesmas/notification-02.wav
snakejazz/sounds/rhodesmas/original_readme_and_license.txt
snakejazz/sounds/rhodesmas/score-counter-01.wav
snakejazz/sounds/rhodesmas/searching-01.wav
snakejazz/sounds/rhodesmas/searching-02.wav
snakejazz/sounds/rhodesmas/searching-03.wav
snakejazz/sounds/rhodesmas/success-01.wav
snakejazz/sounds/rhodesmas/success-02.wav
snakejazz/sounds/rhodesmas/success-03.wav
snakejazz/sounds/rhodesmas/success-04.wav
snakejazz/sounds/rhodesmas/win-01.wav
snakejazz/sounds/rhodesmas/win-02.wav
snakejazz/sounds/rhodesmas/win-04.wav