Metadata-Version: 2.1
Name: snakejazz
Version: 0.1.1
Summary: Decorators for sound reproduction.
Home-page: https://github.com/mchalela/SnakeJazz
Author: Martin Chalela
Author-email: tinchochalela@gmail.com
License: MIT
Keywords: snakejazz,snake,jazz,decorator,sound,music
Platform: UNKNOWN
Classifier: Development Status :: 4 - Beta
Classifier: Intended Audience :: Education
Classifier: Intended Audience :: Science/Research
Classifier: License :: OSI Approved :: MIT License
Classifier: Operating System :: OS Independent
Classifier: Programming Language :: Python
Classifier: Programming Language :: Python :: 3.8
Classifier: Programming Language :: Python :: Implementation :: CPython
Classifier: Topic :: Games/Entertainment
Classifier: Topic :: Multimedia :: Sound/Audio
Classifier: Topic :: Multimedia :: Video
